denodo_sqlalchemy-20240229-py3.11-nspkg.pth
denodo/sqlalchemy/LICENSE
denodo/sqlalchemy/__init__.py
denodo/sqlalchemy/array.py
denodo/sqlalchemy/asyncpg.py
denodo/sqlalchemy/base.py
denodo/sqlalchemy/dml.py
denodo/sqlalchemy/ext.py
denodo/sqlalchemy/jsond.py
denodo/sqlalchemy/pg8000.py
denodo/sqlalchemy/psycopg2.py
denodo/sqlalchemy/psycopg2cffi.py
denodo/sqlalchemy/pygresql.py
denodo/sqlalchemy/pypostgresql.py
denodo/sqlalchemy/ranges.py
denodo/sqlalchemy/setup.py
denodo_sqlalchemy-20240229.dist-info/AUTHORS
denodo_sqlalchemy-20240229.dist-info/AUTHORS-denodo
denodo_sqlalchemy-20240229.dist-info/LICENSE
denodo_sqlalchemy-20240229.dist-info/METADATA
denodo_sqlalchemy-20240229.dist-info/NOTICE.txt
denodo_sqlalchemy-20240229.dist-info/WHEEL
denodo_sqlalchemy-20240229.dist-info/entry_points.txt
denodo_sqlalchemy-20240229.dist-info/namespace_packages.txt
denodo_sqlalchemy-20240229.dist-info/top_level.txt
denodo_sqlalchemy-20240229.dist-info/RECORD
