Metadata-Version: 2.1
Name: denodo-sqlalchemy
Version: 20240229
Summary: Denodo Dialect for SQLAlchemy
Home-page: https://www.denodo.com
Download-URL: https://www.denodo.com
Author: Denodo Research Labs
Author-email: research.labs@denodo.com
License: MIT license
Keywords: Denodo db database
Classifier: Development Status :: 5 - Production/Stable
Classifier: Intended Audience :: Developers
Classifier: Intended Audience :: Information Technology
Classifier: License :: OSI Approved :: MIT License
Classifier: Operating System :: OS Independent
Classifier: Programming Language :: Python :: 3.7
Classifier: Programming Language :: Python :: 3.8
Classifier: Programming Language :: Python :: 3.9
Classifier: Topic :: Database
Classifier: Topic :: Scientific/Engineering :: Information Analysis
License-File: LICENSE
License-File: NOTICE.txt
License-File: AUTHORS
License-File: AUTHORS-denodo
Requires-Dist: sqlalchemy <2.0.0,>=1.4.0
Requires-Dist: psycopg2-binary >=2.7
Provides-Extra: development
Requires-Dist: pytest ; extra == 'development'
